apisix_client/__init__.py
apisix_client/client.py
apisix_client/consumer.py
apisix_client/routes.py
apisix_client/ssl.py
apisix_client/upstream.py
apisix_client/utils.py
apisix_python_client-0.1.0.dist-info/licenses/LICENSE
tests/__init__.py
tests/test_client.py
tests/test_routes.py
tests/test_upstream.py
apisix_python_client-0.1.0.dist-info/METADATA
apisix_python_client-0.1.0.dist-info/WHEEL
apisix_python_client-0.1.0.dist-info/top_level.txt
apisix_python_client-0.1.0.dist-info/RECORD
