Metadata-Version: 2.4
Name: apisix-python-client
Version: 0.1.0
Summary: A simple Python client for Apache APISIX
Home-page: https://github.com/sifoo-31/apisix-python-client
Author: Belhachemi Youcef
Author-email: Belhachemi Youcef <Belhachemi.youcef16@gmail.com>
License: MIT
Project-URL: Homepage, https://github.com/yourusername/apisix-python-client
Project-URL: Bug Tracker, https://github.com/yourusername/apisix-python-client/issues
Keywords: apisix,api,gateway,client
Classifier: Programming Language :: Python :: 3
Classifier: License :: OSI Approved :: MIT License
Classifier: Operating System :: OS Independent
Requires-Python: >=3.6
License-File: LICENSE
Requires-Dist: requests>=2.25.0
Dynamic: author
Dynamic: home-page
Dynamic: license-file
Dynamic: requires-python
